{
  "Parent": "MermaidPlayer",
  "Model": "Characters/Mermaidv2.blockymodel",
  "Texture": "Characters/PlayerTextures/MermaidTextureV2.png",
  "AnimationSets": {
    "Swim": {
      "Animations": [
        {
          "Animation": "Characters/Animations/Mermaids/Mermaidv2_Swimv3.blockyanim",
          "SoundEventId": "SFX_Player_Swim",
          "Speed": 1.1
        }
      ]
    },
    "SwimFast": {
      "Animations": [
        {
          "Animation": "Characters/Animations/Mermaids/Mermaidv2_Swim_Fast.blockyanim",
          "SoundEventId": "SFX_Player_Swim_Fast",
          "Speed": 1.6
        }
      ]
    },
    "SwimDive": {
      "Animations": [
        {
          "Animation": "Characters/Animations/Mermaids/Mermaidv2_Divev2.blockyanim",
          "SoundEventId": "SFX_Player_Swim",
          "Speed": 1.1
        }
      ]
    },
    "SwimDiveFast": {
      "Animations": [
        {
          "Animation": "Characters/Animations/Mermaids/Mermaidv2_Dive_Fast.blockyanim",
          "SoundEventId": "SFX_Player_Swim_Fast",
          "Speed": 1.6
        }
      ]
    }
  }
}